Metadata-Version: 1.1
Name: whatifmachine
Version: 0.1.0
Summary: UNKNOWN
Home-page: https://github.com/MarkCBell/whatifmachine
Author: Mark Bell
Author-email: mcbell@illinois.edu
License: MIT License
Keywords: profiling
Platform: UNKNOWN
Classifier: Development Status :: 4 - Beta
Classifier: Intended Audience :: Education
Classifier: Intended Audience :: Science/Research
Classifier: License :: OSI Approved :: MIT License
Classifier: Natural Language :: English
Classifier: Operating System :: OS Independent
Classifier: Programming Language :: Python
Classifier: Topic :: Scientific/Engineering :: Mathematics
